sfollow/__init__.py
sfollow/__main__.py
sfollow/sfollow.py
sfollow/terminal.py
sfollow-0.2.dist-info/entry_points.txt
sfollow-0.2.dist-info/LICENSE
sfollow-0.2.dist-info/WHEEL
sfollow-0.2.dist-info/METADATA
sfollow-0.2.dist-info/RECORD
