Metadata-Version: 2.1
Name: sfollow
Version: 0.2
Summary: Follow the output of a Slurm batch job
Author-email: European XFEL GmbH <da-support@xfel.eu>
Classifier: License :: OSI Approved :: BSD License
Project-URL: Home, https://github.com/European-XFEL/sfollow
